CHANGES.txt
LICENSE.txt
MANIFEST.in
README.rst
requirements.txt
setup.py
gpx2spatialite/__init__.py
gpx2spatialite/cmdline.py
gpx2spatialite/db.py
gpx2spatialite/db_helper.py
gpx2spatialite/gpx.py
gpx2spatialite/gpx2spatialite.py
gpx2spatialite/helper.py
gpx2spatialite/spatialite_finder.py
gpx2spatialite.egg-info/PKG-INFO
gpx2spatialite.egg-info/SOURCES.txt
gpx2spatialite.egg-info/dependency_links.txt
gpx2spatialite.egg-info/entry_points.txt
gpx2spatialite.egg-info/not-zip-safe
gpx2spatialite.egg-info/requires.txt
gpx2spatialite.egg-info/top_level.txt
gpx2spatialite/data/sql/create_db.sql
gpx2spatialite/data/sql/drop_db.sql
gpx2spatialite/data/sql/insert_citydefs.sql