Metadata-Version: 1.1
Name: gpx2spatialite
Version: 0.8.2
Summary: gpx2spatialite
Home-page: https://github.com/ptrv/gpx2spatialite
Author: Peter Vasil, Daniel Belasco Rogers
Author-email: mail@petervasil.net
License: GPLv3
Download-URL: https://github.com/ptrv/gpx2spatialite
Platform: UNKNOWN
Classifier: License :: OSI Approved :: GNU General Public License v3 (GPLv3)
Classifier: Programming Language :: Python :: 2.7
Classifier: Programming Language :: Python :: 2 :: Only
Classifier: Topic :: Scientific/Engineering :: GIS
